pyflowater/__init__.py
pyflowater/const.py
pyflowater/flostream.py
pyflowater-0.5.2.dist-info/LICENSE.md
pyflowater-0.5.2.dist-info/METADATA
pyflowater-0.5.2.dist-info/WHEEL
pyflowater-0.5.2.dist-info/top_level.txt
pyflowater-0.5.2.dist-info/zip-safe
pyflowater-0.5.2.dist-info/RECORD
