Metadata-Version: 2.1
Name: pyflowater
Version: 0.5.2
Summary: Python interface for Flo by Moen API
Home-page: https://github.com/rsnodgrass/pyflowater
Author: Ryan Snodgrass
Author-email: rsnodgrass@gmail.com
License: Apache Software License
Keywords: flo,home automation,water monitoring
Classifier: Programming Language :: Python :: 3
Classifier: License :: OSI Approved :: Apache Software License
Classifier: Operating System :: OS Independent
License-File: LICENSE.md
Requires-Dist: requests (>=2.0)
Requires-Dist: google-cloud-firestore
